{
  "id": 44141533,
  "node_id": "MDEwOlJlcG9zaXRvcnk0NDE0MTUzMw==",
  "name": "TextSurface",
  "full_name": "elevenetc/TextSurface",
  "private": false,
  "owner": {
    "login": "elevenetc",
    "id": 1069159,
    "node_id": "MDQ6VXNlcjEwNjkxNTk=",
    "avatar_url": "https://avatars.githubusercontent.com/u/1069159?v=4",
    "gravatar_id": "",
    "url": "https://api.github.com/users/elevenetc",
    "html_url": "https://github.com/elevenetc",
    "followers_url": "https://api.github.com/users/elevenetc/followers",
    "following_url": "https://api.github.com/users/elevenetc/following{/other_user}",
    "gists_url": "https://api.github.com/users/elevenetc/gists{/gist_id}",
    "starred_url": "https://api.github.com/users/elevenetc/starred{/owner}{/repo}",
    "subscriptions_url": "https://api.github.com/users/elevenetc/subscriptions",
    "organizations_url": "https://api.github.com/users/elevenetc/orgs",
    "repos_url": "https://api.github.com/users/elevenetc/repos",
    "events_url": "https://api.github.com/users/elevenetc/events{/privacy}",
    "received_events_url": "https://api.github.com/users/elevenetc/received_events",
    "type": "User",
    "site_admin": false
  },
  "html_url": "https://github.com/elevenetc/TextSurface",
  "description": "A little animation framework which could help you to show message in a nice looking way",
  "fork": false,
  "url": "https://api.github.com/repos/elevenetc/TextSurface",
  "forks_url": "https://api.github.com/repos/elevenetc/TextSurface/forks",
  "keys_url": "https://api.github.com/repos/elevenetc/TextSurface/keys{/key_id}",
  "collaborators_url": "https://api.github.com/repos/elevenetc/TextSurface/collaborators{/collaborator}",
  "teams_url": "https://api.github.com/repos/elevenetc/TextSurface/teams",
  "hooks_url": "https://api.github.com/repos/elevenetc/TextSurface/hooks",
  "issue_events_url": "https://api.github.com/repos/elevenetc/TextSurface/issues/events{/number}",
  "events_url": "https://api.github.com/repos/elevenetc/TextSurface/events",
  "assignees_url": "https://api.github.com/repos/elevenetc/TextSurface/assignees{/user}",
  "branches_url": "https://api.github.com/repos/elevenetc/TextSurface/branches{/branch}",
  "tags_url": "https://api.github.com/repos/elevenetc/TextSurface/tags",
  "blobs_url": "https://api.github.com/repos/elevenetc/TextSurface/git/blobs{/sha}",
  "git_tags_url": "https://api.github.com/repos/elevenetc/TextSurface/git/tags{/sha}",
  "git_refs_url": "https://api.github.com/repos/elevenetc/TextSurface/git/refs{/sha}",
  "trees_url": "https://api.github.com/repos/elevenetc/TextSurface/git/trees{/sha}",
  "statuses_url": "https://api.github.com/repos/elevenetc/TextSurface/statuses/{sha}",
  "languages_url": "https://api.github.com/repos/elevenetc/TextSurface/languages",
  "stargazers_url": "https://api.github.com/repos/elevenetc/TextSurface/stargazers",
  "contributors_url": "https://api.github.com/repos/elevenetc/TextSurface/contributors",
  "subscribers_url": "https://api.github.com/repos/elevenetc/TextSurface/subscribers",
  "subscription_url": "https://api.github.com/repos/elevenetc/TextSurface/subscription",
  "commits_url": "https://api.github.com/repos/elevenetc/TextSurface/commits{/sha}",
  "git_commits_url": "https://api.github.com/repos/elevenetc/TextSurface/git/commits{/sha}",
  "comments_url": "https://api.github.com/repos/elevenetc/TextSurface/comments{/number}",
  "issue_comment_url": "https://api.github.com/repos/elevenetc/TextSurface/issues/comments{/number}",
  "contents_url": "https://api.github.com/repos/elevenetc/TextSurface/contents/{+path}",
  "compare_url": "https://api.github.com/repos/elevenetc/TextSurface/compare/{base}...{head}",
  "merges_url": "https://api.github.com/repos/elevenetc/TextSurface/merges",
  "archive_url": "https://api.github.com/repos/elevenetc/TextSurface/{archive_format}{/ref}",
  "downloads_url": "https://api.github.com/repos/elevenetc/TextSurface/downloads",
  "issues_url": "https://api.github.com/repos/elevenetc/TextSurface/issues{/number}",
  "pulls_url": "https://api.github.com/repos/elevenetc/TextSurface/pulls{/number}",
  "milestones_url": "https://api.github.com/repos/elevenetc/TextSurface/milestones{/number}",
  "notifications_url": "https://api.github.com/repos/elevenetc/TextSurface/notifications{?since,all,participating}",
  "labels_url": "https://api.github.com/repos/elevenetc/TextSurface/labels{/name}",
  "releases_url": "https://api.github.com/repos/elevenetc/TextSurface/releases{/id}",
  "deployments_url": "https://api.github.com/repos/elevenetc/TextSurface/deployments",
  "created_at": "2015-10-13T00:21:46Z",
  "updated_at": "2023-02-17T08:30:01Z",
  "pushed_at": "2021-02-17T01:52:27Z",
  "git_url": "git://github.com/elevenetc/TextSurface.git",
  "ssh_url": "git@github.com:elevenetc/TextSurface.git",
  "clone_url": "https://github.com/elevenetc/TextSurface.git",
  "svn_url": "https://github.com/elevenetc/TextSurface",
  "homepage": "",
  "size": 2418,
  "stargazers_count": 2333,
  "watchers_count": 2333,
  "language": "Java",
  "has_issues": true,
  "has_projects": true,
  "has_downloads": true,
  "has_wiki": true,
  "has_pages": false,
  "has_discussions": false,
  "forks_count": 262,
  "mirror_url": null,
  "archived": false,
  "disabled": false,
  "open_issues_count": 9,
  "license": null,
  "allow_forking": true,
  "is_template": false,
  "web_commit_signoff_required": false,
  "topics": [
    "android",
    "android-library",
    "android-ui",
    "animation",
    "animation-framework"
  ],
  "visibility": "public",
  "forks": 262,
  "open_issues": 9,
  "watchers": 2333,
  "default_branch": "master",
  "permissions": {
    "admin": false,
    "maintain": false,
    "push": false,
    "triage": false,
    "pull": false
  },
  "_index": 1442
}