{
  "id": 63539055,
  "node_id": "MDEwOlJlcG9zaXRvcnk2MzUzOTA1NQ==",
  "name": "awesome-mac",
  "full_name": "jaywcjlove/awesome-mac",
  "private": false,
  "owner": {
    "login": "jaywcjlove",
    "id": 1680273,
    "node_id": "MDQ6VXNlcjE2ODAyNzM=",
    "avatar_url": "https://avatars.githubusercontent.com/u/1680273?v=4",
    "gravatar_id": "",
    "url": "https://api.github.com/users/jaywcjlove",
    "html_url": "https://github.com/jaywcjlove",
    "followers_url": "https://api.github.com/users/jaywcjlove/followers",
    "following_url": "https://api.github.com/users/jaywcjlove/following{/other_user}",
    "gists_url": "https://api.github.com/users/jaywcjlove/gists{/gist_id}",
    "starred_url": "https://api.github.com/users/jaywcjlove/starred{/owner}{/repo}",
    "subscriptions_url": "https://api.github.com/users/jaywcjlove/subscriptions",
    "organizations_url": "https://api.github.com/users/jaywcjlove/orgs",
    "repos_url": "https://api.github.com/users/jaywcjlove/repos",
    "events_url": "https://api.github.com/users/jaywcjlove/events{/privacy}",
    "received_events_url": "https://api.github.com/users/jaywcjlove/received_events",
    "type": "User",
    "site_admin": false
  },
  "html_url": "https://github.com/jaywcjlove/awesome-mac",
  "description": " Now we have become very big, Different from the original idea. Collect premium software in various categories.",
  "fork": false,
  "url": "https://api.github.com/repos/jaywcjlove/awesome-mac",
  "forks_url": "https://api.github.com/repos/jaywcjlove/awesome-mac/forks",
  "keys_url": "https://api.github.com/repos/jaywcjlove/awesome-mac/keys{/key_id}",
  "collaborators_url": "https://api.github.com/repos/jaywcjlove/awesome-mac/collaborators{/collaborator}",
  "teams_url": "https://api.github.com/repos/jaywcjlove/awesome-mac/teams",
  "hooks_url": "https://api.github.com/repos/jaywcjlove/awesome-mac/hooks",
  "issue_events_url": "https://api.github.com/repos/jaywcjlove/awesome-mac/issues/events{/number}",
  "events_url": "https://api.github.com/repos/jaywcjlove/awesome-mac/events",
  "assignees_url": "https://api.github.com/repos/jaywcjlove/awesome-mac/assignees{/user}",
  "branches_url": "https://api.github.com/repos/jaywcjlove/awesome-mac/branches{/branch}",
  "tags_url": "https://api.github.com/repos/jaywcjlove/awesome-mac/tags",
  "blobs_url": "https://api.github.com/repos/jaywcjlove/awesome-mac/git/blobs{/sha}",
  "git_tags_url": "https://api.github.com/repos/jaywcjlove/awesome-mac/git/tags{/sha}",
  "git_refs_url": "https://api.github.com/repos/jaywcjlove/awesome-mac/git/refs{/sha}",
  "trees_url": "https://api.github.com/repos/jaywcjlove/awesome-mac/git/trees{/sha}",
  "statuses_url": "https://api.github.com/repos/jaywcjlove/awesome-mac/statuses/{sha}",
  "languages_url": "https://api.github.com/repos/jaywcjlove/awesome-mac/languages",
  "stargazers_url": "https://api.github.com/repos/jaywcjlove/awesome-mac/stargazers",
  "contributors_url": "https://api.github.com/repos/jaywcjlove/awesome-mac/contributors",
  "subscribers_url": "https://api.github.com/repos/jaywcjlove/awesome-mac/subscribers",
  "subscription_url": "https://api.github.com/repos/jaywcjlove/awesome-mac/subscription",
  "commits_url": "https://api.github.com/repos/jaywcjlove/awesome-mac/commits{/sha}",
  "git_commits_url": "https://api.github.com/repos/jaywcjlove/awesome-mac/git/commits{/sha}",
  "comments_url": "https://api.github.com/repos/jaywcjlove/awesome-mac/comments{/number}",
  "issue_comment_url": "https://api.github.com/repos/jaywcjlove/awesome-mac/issues/comments{/number}",
  "contents_url": "https://api.github.com/repos/jaywcjlove/awesome-mac/contents/{+path}",
  "compare_url": "https://api.github.com/repos/jaywcjlove/awesome-mac/compare/{base}...{head}",
  "merges_url": "https://api.github.com/repos/jaywcjlove/awesome-mac/merges",
  "archive_url": "https://api.github.com/repos/jaywcjlove/awesome-mac/{archive_format}{/ref}",
  "downloads_url": "https://api.github.com/repos/jaywcjlove/awesome-mac/downloads",
  "issues_url": "https://api.github.com/repos/jaywcjlove/awesome-mac/issues{/number}",
  "pulls_url": "https://api.github.com/repos/jaywcjlove/awesome-mac/pulls{/number}",
  "milestones_url": "https://api.github.com/repos/jaywcjlove/awesome-mac/milestones{/number}",
  "notifications_url": "https://api.github.com/repos/jaywcjlove/awesome-mac/notifications{?since,all,participating}",
  "labels_url": "https://api.github.com/repos/jaywcjlove/awesome-mac/labels{/name}",
  "releases_url": "https://api.github.com/repos/jaywcjlove/awesome-mac/releases{/id}",
  "deployments_url": "https://api.github.com/repos/jaywcjlove/awesome-mac/deployments",
  "created_at": "2016-07-17T15:33:47Z",
  "updated_at": "2023-07-19T03:02:38Z",
  "pushed_at": "2023-07-18T22:28:27Z",
  "git_url": "git://github.com/jaywcjlove/awesome-mac.git",
  "ssh_url": "git@github.com:jaywcjlove/awesome-mac.git",
  "clone_url": "https://github.com/jaywcjlove/awesome-mac.git",
  "svn_url": "https://github.com/jaywcjlove/awesome-mac",
  "homepage": "https://git.io/macx",
  "size": 10813,
  "stargazers_count": 62074,
  "watchers_count": 62074,
  "language": "JavaScript",
  "has_issues": true,
  "has_projects": true,
  "has_downloads": true,
  "has_wiki": true,
  "has_pages": true,
  "has_discussions": false,
  "forks_count": 5914,
  "mirror_url": null,
  "archived": false,
  "disabled": false,
  "open_issues_count": 139,
  "license": {
    "key": "cc0-1.0",
    "name": "Creative Commons Zero v1.0 Universal",
    "spdx_id": "CC0-1.0",
    "url": "https://api.github.com/licenses/cc0-1.0",
    "node_id": "MDc6TGljZW5zZTY="
  },
  "allow_forking": true,
  "is_template": false,
  "web_commit_signoff_required": false,
  "topics": [
    "apple",
    "awesome",
    "awesome-list",
    "awesome-lists",
    "list",
    "mac",
    "mac-osx",
    "macos",
    "macosx",
    "software"
  ],
  "visibility": "public",
  "forks": 5914,
  "open_issues": 139,
  "watchers": 62074,
  "default_branch": "master",
  "permissions": {
    "admin": false,
    "maintain": false,
    "push": false,
    "triage": false,
    "pull": false
  },
  "_index": 792
}