{
  "id": 203782427,
  "node_id": "MDEwOlJlcG9zaXRvcnkyMDM3ODI0Mjc=",
  "name": "Postman",
  "full_name": "mertceyhan/Postman",
  "private": false,
  "owner": {
    "login": "mertceyhan",
    "id": 22434597,
    "node_id": "MDQ6VXNlcjIyNDM0NTk3",
    "avatar_url": "https://avatars.githubusercontent.com/u/22434597?v=4",
    "gravatar_id": "",
    "url": "https://api.github.com/users/mertceyhan",
    "html_url": "https://github.com/mertceyhan",
    "followers_url": "https://api.github.com/users/mertceyhan/followers",
    "following_url": "https://api.github.com/users/mertceyhan/following{/other_user}",
    "gists_url": "https://api.github.com/users/mertceyhan/gists{/gist_id}",
    "starred_url": "https://api.github.com/users/mertceyhan/starred{/owner}{/repo}",
    "subscriptions_url": "https://api.github.com/users/mertceyhan/subscriptions",
    "organizations_url": "https://api.github.com/users/mertceyhan/orgs",
    "repos_url": "https://api.github.com/users/mertceyhan/repos",
    "events_url": "https://api.github.com/users/mertceyhan/events{/privacy}",
    "received_events_url": "https://api.github.com/users/mertceyhan/received_events",
    "type": "User",
    "site_admin": false
  },
  "html_url": "https://github.com/mertceyhan/Postman",
  "description": "Postman is a reactive One-tap SMS verification library. This library allows the usage of RxJava with The SMS User Consent API",
  "fork": false,
  "url": "https://api.github.com/repos/mertceyhan/Postman",
  "forks_url": "https://api.github.com/repos/mertceyhan/Postman/forks",
  "keys_url": "https://api.github.com/repos/mertceyhan/Postman/keys{/key_id}",
  "collaborators_url": "https://api.github.com/repos/mertceyhan/Postman/collaborators{/collaborator}",
  "teams_url": "https://api.github.com/repos/mertceyhan/Postman/teams",
  "hooks_url": "https://api.github.com/repos/mertceyhan/Postman/hooks",
  "issue_events_url": "https://api.github.com/repos/mertceyhan/Postman/issues/events{/number}",
  "events_url": "https://api.github.com/repos/mertceyhan/Postman/events",
  "assignees_url": "https://api.github.com/repos/mertceyhan/Postman/assignees{/user}",
  "branches_url": "https://api.github.com/repos/mertceyhan/Postman/branches{/branch}",
  "tags_url": "https://api.github.com/repos/mertceyhan/Postman/tags",
  "blobs_url": "https://api.github.com/repos/mertceyhan/Postman/git/blobs{/sha}",
  "git_tags_url": "https://api.github.com/repos/mertceyhan/Postman/git/tags{/sha}",
  "git_refs_url": "https://api.github.com/repos/mertceyhan/Postman/git/refs{/sha}",
  "trees_url": "https://api.github.com/repos/mertceyhan/Postman/git/trees{/sha}",
  "statuses_url": "https://api.github.com/repos/mertceyhan/Postman/statuses/{sha}",
  "languages_url": "https://api.github.com/repos/mertceyhan/Postman/languages",
  "stargazers_url": "https://api.github.com/repos/mertceyhan/Postman/stargazers",
  "contributors_url": "https://api.github.com/repos/mertceyhan/Postman/contributors",
  "subscribers_url": "https://api.github.com/repos/mertceyhan/Postman/subscribers",
  "subscription_url": "https://api.github.com/repos/mertceyhan/Postman/subscription",
  "commits_url": "https://api.github.com/repos/mertceyhan/Postman/commits{/sha}",
  "git_commits_url": "https://api.github.com/repos/mertceyhan/Postman/git/commits{/sha}",
  "comments_url": "https://api.github.com/repos/mertceyhan/Postman/comments{/number}",
  "issue_comment_url": "https://api.github.com/repos/mertceyhan/Postman/issues/comments{/number}",
  "contents_url": "https://api.github.com/repos/mertceyhan/Postman/contents/{+path}",
  "compare_url": "https://api.github.com/repos/mertceyhan/Postman/compare/{base}...{head}",
  "merges_url": "https://api.github.com/repos/mertceyhan/Postman/merges",
  "archive_url": "https://api.github.com/repos/mertceyhan/Postman/{archive_format}{/ref}",
  "downloads_url": "https://api.github.com/repos/mertceyhan/Postman/downloads",
  "issues_url": "https://api.github.com/repos/mertceyhan/Postman/issues{/number}",
  "pulls_url": "https://api.github.com/repos/mertceyhan/Postman/pulls{/number}",
  "milestones_url": "https://api.github.com/repos/mertceyhan/Postman/milestones{/number}",
  "notifications_url": "https://api.github.com/repos/mertceyhan/Postman/notifications{?since,all,participating}",
  "labels_url": "https://api.github.com/repos/mertceyhan/Postman/labels{/name}",
  "releases_url": "https://api.github.com/repos/mertceyhan/Postman/releases{/id}",
  "deployments_url": "https://api.github.com/repos/mertceyhan/Postman/deployments",
  "created_at": "2019-08-22T11:37:05Z",
  "updated_at": "2023-03-27T20:37:45Z",
  "pushed_at": "2022-07-17T13:02:48Z",
  "git_url": "git://github.com/mertceyhan/Postman.git",
  "ssh_url": "git@github.com:mertceyhan/Postman.git",
  "clone_url": "https://github.com/mertceyhan/Postman.git",
  "svn_url": "https://github.com/mertceyhan/Postman",
  "homepage": "",
  "size": 1170,
  "stargazers_count": 129,
  "watchers_count": 129,
  "language": "Kotlin",
  "has_issues": true,
  "has_projects": true,
  "has_downloads": true,
  "has_wiki": true,
  "has_pages": false,
  "has_discussions": false,
  "forks_count": 7,
  "mirror_url": null,
  "archived": false,
  "disabled": false,
  "open_issues_count": 0,
  "license": null,
  "allow_forking": true,
  "is_template": false,
  "web_commit_signoff_required": false,
  "topics": [],
  "visibility": "public",
  "forks": 7,
  "open_issues": 0,
  "watchers": 129,
  "default_branch": "master",
  "permissions": {
    "admin": false,
    "maintain": false,
    "push": false,
    "triage": false,
    "pull": false
  },
  "_index": 2162
}