{
  "id": 41718185,
  "node_id": "MDEwOlJlcG9zaXRvcnk0MTcxODE4NQ==",
  "name": "awesome-angular",
  "full_name": "PatrickJS/awesome-angular",
  "private": false,
  "owner": {
    "login": "PatrickJS",
    "id": 1016365,
    "node_id": "MDQ6VXNlcjEwMTYzNjU=",
    "avatar_url": "https://avatars.githubusercontent.com/u/1016365?v=4",
    "gravatar_id": "",
    "url": "https://api.github.com/users/PatrickJS",
    "html_url": "https://github.com/PatrickJS",
    "followers_url": "https://api.github.com/users/PatrickJS/followers",
    "following_url": "https://api.github.com/users/PatrickJS/following{/other_user}",
    "gists_url": "https://api.github.com/users/PatrickJS/gists{/gist_id}",
    "starred_url": "https://api.github.com/users/PatrickJS/starred{/owner}{/repo}",
    "subscriptions_url": "https://api.github.com/users/PatrickJS/subscriptions",
    "organizations_url": "https://api.github.com/users/PatrickJS/orgs",
    "repos_url": "https://api.github.com/users/PatrickJS/repos",
    "events_url": "https://api.github.com/users/PatrickJS/events{/privacy}",
    "received_events_url": "https://api.github.com/users/PatrickJS/received_events",
    "type": "User",
    "site_admin": false
  },
  "html_url": "https://github.com/PatrickJS/awesome-angular",
  "description": ":page_facing_up: A curated list of awesome Angular resources",
  "fork": false,
  "url": "https://api.github.com/repos/PatrickJS/awesome-angular",
  "forks_url": "https://api.github.com/repos/PatrickJS/awesome-angular/forks",
  "keys_url": "https://api.github.com/repos/PatrickJS/awesome-angular/keys{/key_id}",
  "collaborators_url": "https://api.github.com/repos/PatrickJS/awesome-angular/collaborators{/collaborator}",
  "teams_url": "https://api.github.com/repos/PatrickJS/awesome-angular/teams",
  "hooks_url": "https://api.github.com/repos/PatrickJS/awesome-angular/hooks",
  "issue_events_url": "https://api.github.com/repos/PatrickJS/awesome-angular/issues/events{/number}",
  "events_url": "https://api.github.com/repos/PatrickJS/awesome-angular/events",
  "assignees_url": "https://api.github.com/repos/PatrickJS/awesome-angular/assignees{/user}",
  "branches_url": "https://api.github.com/repos/PatrickJS/awesome-angular/branches{/branch}",
  "tags_url": "https://api.github.com/repos/PatrickJS/awesome-angular/tags",
  "blobs_url": "https://api.github.com/repos/PatrickJS/awesome-angular/git/blobs{/sha}",
  "git_tags_url": "https://api.github.com/repos/PatrickJS/awesome-angular/git/tags{/sha}",
  "git_refs_url": "https://api.github.com/repos/PatrickJS/awesome-angular/git/refs{/sha}",
  "trees_url": "https://api.github.com/repos/PatrickJS/awesome-angular/git/trees{/sha}",
  "statuses_url": "https://api.github.com/repos/PatrickJS/awesome-angular/statuses/{sha}",
  "languages_url": "https://api.github.com/repos/PatrickJS/awesome-angular/languages",
  "stargazers_url": "https://api.github.com/repos/PatrickJS/awesome-angular/stargazers",
  "contributors_url": "https://api.github.com/repos/PatrickJS/awesome-angular/contributors",
  "subscribers_url": "https://api.github.com/repos/PatrickJS/awesome-angular/subscribers",
  "subscription_url": "https://api.github.com/repos/PatrickJS/awesome-angular/subscription",
  "commits_url": "https://api.github.com/repos/PatrickJS/awesome-angular/commits{/sha}",
  "git_commits_url": "https://api.github.com/repos/PatrickJS/awesome-angular/git/commits{/sha}",
  "comments_url": "https://api.github.com/repos/PatrickJS/awesome-angular/comments{/number}",
  "issue_comment_url": "https://api.github.com/repos/PatrickJS/awesome-angular/issues/comments{/number}",
  "contents_url": "https://api.github.com/repos/PatrickJS/awesome-angular/contents/{+path}",
  "compare_url": "https://api.github.com/repos/PatrickJS/awesome-angular/compare/{base}...{head}",
  "merges_url": "https://api.github.com/repos/PatrickJS/awesome-angular/merges",
  "archive_url": "https://api.github.com/repos/PatrickJS/awesome-angular/{archive_format}{/ref}",
  "downloads_url": "https://api.github.com/repos/PatrickJS/awesome-angular/downloads",
  "issues_url": "https://api.github.com/repos/PatrickJS/awesome-angular/issues{/number}",
  "pulls_url": "https://api.github.com/repos/PatrickJS/awesome-angular/pulls{/number}",
  "milestones_url": "https://api.github.com/repos/PatrickJS/awesome-angular/milestones{/number}",
  "notifications_url": "https://api.github.com/repos/PatrickJS/awesome-angular/notifications{?since,all,participating}",
  "labels_url": "https://api.github.com/repos/PatrickJS/awesome-angular/labels{/name}",
  "releases_url": "https://api.github.com/repos/PatrickJS/awesome-angular/releases{/id}",
  "deployments_url": "https://api.github.com/repos/PatrickJS/awesome-angular/deployments",
  "created_at": "2015-09-01T05:12:10Z",
  "updated_at": "2023-08-29T22:49:04Z",
  "pushed_at": "2023-08-07T12:21:16Z",
  "git_url": "git://github.com/PatrickJS/awesome-angular.git",
  "ssh_url": "git@github.com:PatrickJS/awesome-angular.git",
  "clone_url": "https://github.com/PatrickJS/awesome-angular.git",
  "svn_url": "https://github.com/PatrickJS/awesome-angular",
  "homepage": "https://patrickjs.github.io/awesome-angular/",
  "size": 956,
  "stargazers_count": 9024,
  "watchers_count": 9024,
  "language": "HTML",
  "has_issues": true,
  "has_projects": false,
  "has_downloads": true,
  "has_wiki": false,
  "has_pages": true,
  "has_discussions": false,
  "forks_count": 1329,
  "mirror_url": null,
  "archived": false,
  "disabled": false,
  "open_issues_count": 14,
  "license": {
    "key": "cc0-1.0",
    "name": "Creative Commons Zero v1.0 Universal",
    "spdx_id": "CC0-1.0",
    "url": "https://api.github.com/licenses/cc0-1.0",
    "node_id": "MDc6TGljZW5zZTY="
  },
  "allow_forking": true,
  "is_template": false,
  "web_commit_signoff_required": false,
  "topics": [
    "angular",
    "angular-components",
    "angular10",
    "angular11",
    "angular2",
    "angular4",
    "angular9",
    "awesome",
    "awesome-list"
  ],
  "visibility": "public",
  "forks": 1329,
  "open_issues": 14,
  "watchers": 9024,
  "default_branch": "gh-pages",
  "permissions": {
    "admin": false,
    "maintain": false,
    "push": false,
    "triage": false,
    "pull": false
  },
  "_index": 2951
}