{
  "id": 153999249,
  "node_id": "MDEwOlJlcG9zaXRvcnkxNTM5OTkyNDk=",
  "name": "nuxt-purgecss",
  "full_name": "Developmint/nuxt-purgecss",
  "private": false,
  "owner": {
    "login": "Developmint",
    "id": 29969219,
    "node_id": "MDEyOk9yZ2FuaXphdGlvbjI5OTY5MjE5",
    "avatar_url": "https://avatars.githubusercontent.com/u/29969219?v=4",
    "gravatar_id": "",
    "url": "https://api.github.com/users/Developmint",
    "html_url": "https://github.com/Developmint",
    "followers_url": "https://api.github.com/users/Developmint/followers",
    "following_url": "https://api.github.com/users/Developmint/following{/other_user}",
    "gists_url": "https://api.github.com/users/Developmint/gists{/gist_id}",
    "starred_url": "https://api.github.com/users/Developmint/starred{/owner}{/repo}",
    "subscriptions_url": "https://api.github.com/users/Developmint/subscriptions",
    "organizations_url": "https://api.github.com/users/Developmint/orgs",
    "repos_url": "https://api.github.com/users/Developmint/repos",
    "events_url": "https://api.github.com/users/Developmint/events{/privacy}",
    "received_events_url": "https://api.github.com/users/Developmint/received_events",
    "type": "Organization",
    "site_admin": false
  },
  "html_url": "https://github.com/Developmint/nuxt-purgecss",
  "description": "Drop superfluous CSS! A neat PurgeCSS wrapper for Nuxt.js",
  "fork": false,
  "url": "https://api.github.com/repos/Developmint/nuxt-purgecss",
  "forks_url": "https://api.github.com/repos/Developmint/nuxt-purgecss/forks",
  "keys_url": "https://api.github.com/repos/Developmint/nuxt-purgecss/keys{/key_id}",
  "collaborators_url": "https://api.github.com/repos/Developmint/nuxt-purgecss/collaborators{/collaborator}",
  "teams_url": "https://api.github.com/repos/Developmint/nuxt-purgecss/teams",
  "hooks_url": "https://api.github.com/repos/Developmint/nuxt-purgecss/hooks",
  "issue_events_url": "https://api.github.com/repos/Developmint/nuxt-purgecss/issues/events{/number}",
  "events_url": "https://api.github.com/repos/Developmint/nuxt-purgecss/events",
  "assignees_url": "https://api.github.com/repos/Developmint/nuxt-purgecss/assignees{/user}",
  "branches_url": "https://api.github.com/repos/Developmint/nuxt-purgecss/branches{/branch}",
  "tags_url": "https://api.github.com/repos/Developmint/nuxt-purgecss/tags",
  "blobs_url": "https://api.github.com/repos/Developmint/nuxt-purgecss/git/blobs{/sha}",
  "git_tags_url": "https://api.github.com/repos/Developmint/nuxt-purgecss/git/tags{/sha}",
  "git_refs_url": "https://api.github.com/repos/Developmint/nuxt-purgecss/git/refs{/sha}",
  "trees_url": "https://api.github.com/repos/Developmint/nuxt-purgecss/git/trees{/sha}",
  "statuses_url": "https://api.github.com/repos/Developmint/nuxt-purgecss/statuses/{sha}",
  "languages_url": "https://api.github.com/repos/Developmint/nuxt-purgecss/languages",
  "stargazers_url": "https://api.github.com/repos/Developmint/nuxt-purgecss/stargazers",
  "contributors_url": "https://api.github.com/repos/Developmint/nuxt-purgecss/contributors",
  "subscribers_url": "https://api.github.com/repos/Developmint/nuxt-purgecss/subscribers",
  "subscription_url": "https://api.github.com/repos/Developmint/nuxt-purgecss/subscription",
  "commits_url": "https://api.github.com/repos/Developmint/nuxt-purgecss/commits{/sha}",
  "git_commits_url": "https://api.github.com/repos/Developmint/nuxt-purgecss/git/commits{/sha}",
  "comments_url": "https://api.github.com/repos/Developmint/nuxt-purgecss/comments{/number}",
  "issue_comment_url": "https://api.github.com/repos/Developmint/nuxt-purgecss/issues/comments{/number}",
  "contents_url": "https://api.github.com/repos/Developmint/nuxt-purgecss/contents/{+path}",
  "compare_url": "https://api.github.com/repos/Developmint/nuxt-purgecss/compare/{base}...{head}",
  "merges_url": "https://api.github.com/repos/Developmint/nuxt-purgecss/merges",
  "archive_url": "https://api.github.com/repos/Developmint/nuxt-purgecss/{archive_format}{/ref}",
  "downloads_url": "https://api.github.com/repos/Developmint/nuxt-purgecss/downloads",
  "issues_url": "https://api.github.com/repos/Developmint/nuxt-purgecss/issues{/number}",
  "pulls_url": "https://api.github.com/repos/Developmint/nuxt-purgecss/pulls{/number}",
  "milestones_url": "https://api.github.com/repos/Developmint/nuxt-purgecss/milestones{/number}",
  "notifications_url": "https://api.github.com/repos/Developmint/nuxt-purgecss/notifications{?since,all,participating}",
  "labels_url": "https://api.github.com/repos/Developmint/nuxt-purgecss/labels{/name}",
  "releases_url": "https://api.github.com/repos/Developmint/nuxt-purgecss/releases{/id}",
  "deployments_url": "https://api.github.com/repos/Developmint/nuxt-purgecss/deployments",
  "created_at": "2018-10-21T11:07:01Z",
  "updated_at": "2023-12-22T16:56:00Z",
  "pushed_at": "2024-01-16T18:56:11Z",
  "git_url": "git://github.com/Developmint/nuxt-purgecss.git",
  "ssh_url": "git@github.com:Developmint/nuxt-purgecss.git",
  "clone_url": "https://github.com/Developmint/nuxt-purgecss.git",
  "svn_url": "https://github.com/Developmint/nuxt-purgecss",
  "homepage": "",
  "size": 893,
  "stargazers_count": 460,
  "watchers_count": 460,
  "language": "TypeScript",
  "has_issues": true,
  "has_projects": true,
  "has_downloads": true,
  "has_wiki": false,
  "has_pages": false,
  "has_discussions": false,
  "forks_count": 19,
  "mirror_url": null,
  "archived": false,
  "disabled": false,
  "open_issues_count": 24,
  "license": {
    "key": "mit",
    "name": "MIT License",
    "spdx_id": "MIT",
    "url": "https://api.github.com/licenses/mit",
    "node_id": "MDc6TGljZW5zZTEz"
  },
  "allow_forking": true,
  "is_template": false,
  "web_commit_signoff_required": false,
  "topics": [
    "hacktoberfest",
    "nuxt",
    "nuxt-module",
    "nuxt-purgecss",
    "nuxtjs",
    "postcss",
    "purgecss",
    "vue",
    "webpack"
  ],
  "visibility": "public",
  "forks": 19,
  "open_issues": 24,
  "watchers": 460,
  "default_branch": "main",
  "permissions": {
    "admin": false,
    "maintain": false,
    "push": false,
    "triage": false,
    "pull": false
  },
  "_index": 1093
}