{
  "id": 24648268,
  "node_id": "MDEwOlJlcG9zaXRvcnkyNDY0ODI2OA==",
  "name": "kenburns",
  "full_name": "gre/kenburns",
  "private": false,
  "owner": {
    "login": "gre",
    "id": 211411,
    "node_id": "MDQ6VXNlcjIxMTQxMQ==",
    "avatar_url": "https://avatars.githubusercontent.com/u/211411?v=4",
    "gravatar_id": "",
    "url": "https://api.github.com/users/gre",
    "html_url": "https://github.com/gre",
    "followers_url": "https://api.github.com/users/gre/followers",
    "following_url": "https://api.github.com/users/gre/following{/other_user}",
    "gists_url": "https://api.github.com/users/gre/gists{/gist_id}",
    "starred_url": "https://api.github.com/users/gre/starred{/owner}{/repo}",
    "subscriptions_url": "https://api.github.com/users/gre/subscriptions",
    "organizations_url": "https://api.github.com/users/gre/orgs",
    "repos_url": "https://api.github.com/users/gre/repos",
    "events_url": "https://api.github.com/users/gre/events{/privacy}",
    "received_events_url": "https://api.github.com/users/gre/received_events",
    "type": "User",
    "site_admin": false
  },
  "html_url": "https://github.com/gre/kenburns",
  "description": "Ken Burns effect for DOM, Canvas2D, WebGL",
  "fork": false,
  "url": "https://api.github.com/repos/gre/kenburns",
  "forks_url": "https://api.github.com/repos/gre/kenburns/forks",
  "keys_url": "https://api.github.com/repos/gre/kenburns/keys{/key_id}",
  "collaborators_url": "https://api.github.com/repos/gre/kenburns/collaborators{/collaborator}",
  "teams_url": "https://api.github.com/repos/gre/kenburns/teams",
  "hooks_url": "https://api.github.com/repos/gre/kenburns/hooks",
  "issue_events_url": "https://api.github.com/repos/gre/kenburns/issues/events{/number}",
  "events_url": "https://api.github.com/repos/gre/kenburns/events",
  "assignees_url": "https://api.github.com/repos/gre/kenburns/assignees{/user}",
  "branches_url": "https://api.github.com/repos/gre/kenburns/branches{/branch}",
  "tags_url": "https://api.github.com/repos/gre/kenburns/tags",
  "blobs_url": "https://api.github.com/repos/gre/kenburns/git/blobs{/sha}",
  "git_tags_url": "https://api.github.com/repos/gre/kenburns/git/tags{/sha}",
  "git_refs_url": "https://api.github.com/repos/gre/kenburns/git/refs{/sha}",
  "trees_url": "https://api.github.com/repos/gre/kenburns/git/trees{/sha}",
  "statuses_url": "https://api.github.com/repos/gre/kenburns/statuses/{sha}",
  "languages_url": "https://api.github.com/repos/gre/kenburns/languages",
  "stargazers_url": "https://api.github.com/repos/gre/kenburns/stargazers",
  "contributors_url": "https://api.github.com/repos/gre/kenburns/contributors",
  "subscribers_url": "https://api.github.com/repos/gre/kenburns/subscribers",
  "subscription_url": "https://api.github.com/repos/gre/kenburns/subscription",
  "commits_url": "https://api.github.com/repos/gre/kenburns/commits{/sha}",
  "git_commits_url": "https://api.github.com/repos/gre/kenburns/git/commits{/sha}",
  "comments_url": "https://api.github.com/repos/gre/kenburns/comments{/number}",
  "issue_comment_url": "https://api.github.com/repos/gre/kenburns/issues/comments{/number}",
  "contents_url": "https://api.github.com/repos/gre/kenburns/contents/{+path}",
  "compare_url": "https://api.github.com/repos/gre/kenburns/compare/{base}...{head}",
  "merges_url": "https://api.github.com/repos/gre/kenburns/merges",
  "archive_url": "https://api.github.com/repos/gre/kenburns/{archive_format}{/ref}",
  "downloads_url": "https://api.github.com/repos/gre/kenburns/downloads",
  "issues_url": "https://api.github.com/repos/gre/kenburns/issues{/number}",
  "pulls_url": "https://api.github.com/repos/gre/kenburns/pulls{/number}",
  "milestones_url": "https://api.github.com/repos/gre/kenburns/milestones{/number}",
  "notifications_url": "https://api.github.com/repos/gre/kenburns/notifications{?since,all,participating}",
  "labels_url": "https://api.github.com/repos/gre/kenburns/labels{/name}",
  "releases_url": "https://api.github.com/repos/gre/kenburns/releases{/id}",
  "deployments_url": "https://api.github.com/repos/gre/kenburns/deployments",
  "created_at": "2014-09-30T17:37:47Z",
  "updated_at": "2022-09-30T22:44:24Z",
  "pushed_at": "2016-12-23T10:17:18Z",
  "git_url": "git://github.com/gre/kenburns.git",
  "ssh_url": "git@github.com:gre/kenburns.git",
  "clone_url": "https://github.com/gre/kenburns.git",
  "svn_url": "https://github.com/gre/kenburns",
  "homepage": "http://kenburns.surge.sh/",
  "size": 80,
  "stargazers_count": 62,
  "watchers_count": 62,
  "language": "JavaScript",
  "has_issues": true,
  "has_projects": true,
  "has_downloads": true,
  "has_wiki": true,
  "has_pages": false,
  "forks_count": 8,
  "mirror_url": null,
  "archived": false,
  "disabled": false,
  "open_issues_count": 1,
  "license": {
    "key": "isc",
    "name": "ISC License",
    "spdx_id": "ISC",
    "url": "https://api.github.com/licenses/isc",
    "node_id": "MDc6TGljZW5zZTEw"
  },
  "allow_forking": true,
  "is_template": false,
  "web_commit_signoff_required": false,
  "topics": [
    "animation",
    "kenburns"
  ],
  "visibility": "public",
  "forks": 8,
  "open_issues": 1,
  "watchers": 62,
  "default_branch": "master",
  "permissions": {
    "admin": false,
    "maintain": false,
    "push": false,
    "triage": false,
    "pull": false
  },
  "_index": 1805
}