{
  "id": 100240240,
  "node_id": "MDEwOlJlcG9zaXRvcnkxMDAyNDAyNDA=",
  "name": "Album",
  "full_name": "7449/Album",
  "private": false,
  "owner": {
    "login": "7449",
    "id": 16410317,
    "node_id": "MDQ6VXNlcjE2NDEwMzE3",
    "avatar_url": "https://avatars.githubusercontent.com/u/16410317?v=4",
    "gravatar_id": "",
    "url": "https://api.github.com/users/7449",
    "html_url": "https://github.com/7449",
    "followers_url": "https://api.github.com/users/7449/followers",
    "following_url": "https://api.github.com/users/7449/following{/other_user}",
    "gists_url": "https://api.github.com/users/7449/gists{/gist_id}",
    "starred_url": "https://api.github.com/users/7449/starred{/owner}{/repo}",
    "subscriptions_url": "https://api.github.com/users/7449/subscriptions",
    "organizations_url": "https://api.github.com/users/7449/orgs",
    "repos_url": "https://api.github.com/users/7449/repos",
    "events_url": "https://api.github.com/users/7449/events{/privacy}",
    "received_events_url": "https://api.github.com/users/7449/received_events",
    "type": "User",
    "site_admin": false
  },
  "html_url": "https://github.com/7449/Album",
  "description": "android 图片视频加载库，单选，多选，预览，自定义UI，相机，裁剪...等等 适配10-13",
  "fork": false,
  "url": "https://api.github.com/repos/7449/Album",
  "forks_url": "https://api.github.com/repos/7449/Album/forks",
  "keys_url": "https://api.github.com/repos/7449/Album/keys{/key_id}",
  "collaborators_url": "https://api.github.com/repos/7449/Album/collaborators{/collaborator}",
  "teams_url": "https://api.github.com/repos/7449/Album/teams",
  "hooks_url": "https://api.github.com/repos/7449/Album/hooks",
  "issue_events_url": "https://api.github.com/repos/7449/Album/issues/events{/number}",
  "events_url": "https://api.github.com/repos/7449/Album/events",
  "assignees_url": "https://api.github.com/repos/7449/Album/assignees{/user}",
  "branches_url": "https://api.github.com/repos/7449/Album/branches{/branch}",
  "tags_url": "https://api.github.com/repos/7449/Album/tags",
  "blobs_url": "https://api.github.com/repos/7449/Album/git/blobs{/sha}",
  "git_tags_url": "https://api.github.com/repos/7449/Album/git/tags{/sha}",
  "git_refs_url": "https://api.github.com/repos/7449/Album/git/refs{/sha}",
  "trees_url": "https://api.github.com/repos/7449/Album/git/trees{/sha}",
  "statuses_url": "https://api.github.com/repos/7449/Album/statuses/{sha}",
  "languages_url": "https://api.github.com/repos/7449/Album/languages",
  "stargazers_url": "https://api.github.com/repos/7449/Album/stargazers",
  "contributors_url": "https://api.github.com/repos/7449/Album/contributors",
  "subscribers_url": "https://api.github.com/repos/7449/Album/subscribers",
  "subscription_url": "https://api.github.com/repos/7449/Album/subscription",
  "commits_url": "https://api.github.com/repos/7449/Album/commits{/sha}",
  "git_commits_url": "https://api.github.com/repos/7449/Album/git/commits{/sha}",
  "comments_url": "https://api.github.com/repos/7449/Album/comments{/number}",
  "issue_comment_url": "https://api.github.com/repos/7449/Album/issues/comments{/number}",
  "contents_url": "https://api.github.com/repos/7449/Album/contents/{+path}",
  "compare_url": "https://api.github.com/repos/7449/Album/compare/{base}...{head}",
  "merges_url": "https://api.github.com/repos/7449/Album/merges",
  "archive_url": "https://api.github.com/repos/7449/Album/{archive_format}{/ref}",
  "downloads_url": "https://api.github.com/repos/7449/Album/downloads",
  "issues_url": "https://api.github.com/repos/7449/Album/issues{/number}",
  "pulls_url": "https://api.github.com/repos/7449/Album/pulls{/number}",
  "milestones_url": "https://api.github.com/repos/7449/Album/milestones{/number}",
  "notifications_url": "https://api.github.com/repos/7449/Album/notifications{?since,all,participating}",
  "labels_url": "https://api.github.com/repos/7449/Album/labels{/name}",
  "releases_url": "https://api.github.com/repos/7449/Album/releases{/id}",
  "deployments_url": "https://api.github.com/repos/7449/Album/deployments",
  "created_at": "2017-08-14T07:27:06Z",
  "updated_at": "2023-01-30T11:00:51Z",
  "pushed_at": "2023-02-06T10:37:04Z",
  "git_url": "git://github.com/7449/Album.git",
  "ssh_url": "git@github.com:7449/Album.git",
  "clone_url": "https://github.com/7449/Album.git",
  "svn_url": "https://github.com/7449/Album",
  "homepage": "https://7449.github.io/Album",
  "size": 16462,
  "stargazers_count": 61,
  "watchers_count": 61,
  "language": "Kotlin",
  "has_issues": true,
  "has_projects": false,
  "has_downloads": true,
  "has_wiki": false,
  "has_pages": true,
  "has_discussions": false,
  "forks_count": 9,
  "mirror_url": null,
  "archived": false,
  "disabled": false,
  "open_issues_count": 0,
  "license": {
    "key": "mpl-2.0",
    "name": "Mozilla Public License 2.0",
    "spdx_id": "MPL-2.0",
    "url": "https://api.github.com/licenses/mpl-2.0",
    "node_id": "MDc6TGljZW5zZTE0"
  },
  "allow_forking": true,
  "is_template": false,
  "web_commit_signoff_required": false,
  "topics": [
    "album",
    "android",
    "camera",
    "crop-image",
    "gallery",
    "image",
    "imageselector",
    "picture",
    "select",
    "wechat"
  ],
  "visibility": "public",
  "forks": 9,
  "open_issues": 0,
  "watchers": 61,
  "default_branch": "master",
  "permissions": {
    "admin": false,
    "maintain": false,
    "push": false,
    "triage": false,
    "pull": false
  },
  "_index": 2331
}