{
  "id": 108873775,
  "node_id": "MDEwOlJlcG9zaXRvcnkxMDg4NzM3NzU=",
  "name": "remult",
  "full_name": "remult/remult",
  "private": false,
  "owner": {
    "login": "remult",
    "id": 87660479,
    "node_id": "MDEyOk9yZ2FuaXphdGlvbjg3NjYwNDc5",
    "avatar_url": "https://avatars.githubusercontent.com/u/87660479?v=4",
    "gravatar_id": "",
    "url": "https://api.github.com/users/remult",
    "html_url": "https://github.com/remult",
    "followers_url": "https://api.github.com/users/remult/followers",
    "following_url": "https://api.github.com/users/remult/following{/other_user}",
    "gists_url": "https://api.github.com/users/remult/gists{/gist_id}",
    "starred_url": "https://api.github.com/users/remult/starred{/owner}{/repo}",
    "subscriptions_url": "https://api.github.com/users/remult/subscriptions",
    "organizations_url": "https://api.github.com/users/remult/orgs",
    "repos_url": "https://api.github.com/users/remult/repos",
    "events_url": "https://api.github.com/users/remult/events{/privacy}",
    "received_events_url": "https://api.github.com/users/remult/received_events",
    "type": "Organization",
    "site_admin": false
  },
  "html_url": "https://github.com/remult/remult",
  "description": "Full-stack CRUD, simplified, with SSOT TypeScript entities",
  "fork": false,
  "url": "https://api.github.com/repos/remult/remult",
  "forks_url": "https://api.github.com/repos/remult/remult/forks",
  "keys_url": "https://api.github.com/repos/remult/remult/keys{/key_id}",
  "collaborators_url": "https://api.github.com/repos/remult/remult/collaborators{/collaborator}",
  "teams_url": "https://api.github.com/repos/remult/remult/teams",
  "hooks_url": "https://api.github.com/repos/remult/remult/hooks",
  "issue_events_url": "https://api.github.com/repos/remult/remult/issues/events{/number}",
  "events_url": "https://api.github.com/repos/remult/remult/events",
  "assignees_url": "https://api.github.com/repos/remult/remult/assignees{/user}",
  "branches_url": "https://api.github.com/repos/remult/remult/branches{/branch}",
  "tags_url": "https://api.github.com/repos/remult/remult/tags",
  "blobs_url": "https://api.github.com/repos/remult/remult/git/blobs{/sha}",
  "git_tags_url": "https://api.github.com/repos/remult/remult/git/tags{/sha}",
  "git_refs_url": "https://api.github.com/repos/remult/remult/git/refs{/sha}",
  "trees_url": "https://api.github.com/repos/remult/remult/git/trees{/sha}",
  "statuses_url": "https://api.github.com/repos/remult/remult/statuses/{sha}",
  "languages_url": "https://api.github.com/repos/remult/remult/languages",
  "stargazers_url": "https://api.github.com/repos/remult/remult/stargazers",
  "contributors_url": "https://api.github.com/repos/remult/remult/contributors",
  "subscribers_url": "https://api.github.com/repos/remult/remult/subscribers",
  "subscription_url": "https://api.github.com/repos/remult/remult/subscription",
  "commits_url": "https://api.github.com/repos/remult/remult/commits{/sha}",
  "git_commits_url": "https://api.github.com/repos/remult/remult/git/commits{/sha}",
  "comments_url": "https://api.github.com/repos/remult/remult/comments{/number}",
  "issue_comment_url": "https://api.github.com/repos/remult/remult/issues/comments{/number}",
  "contents_url": "https://api.github.com/repos/remult/remult/contents/{+path}",
  "compare_url": "https://api.github.com/repos/remult/remult/compare/{base}...{head}",
  "merges_url": "https://api.github.com/repos/remult/remult/merges",
  "archive_url": "https://api.github.com/repos/remult/remult/{archive_format}{/ref}",
  "downloads_url": "https://api.github.com/repos/remult/remult/downloads",
  "issues_url": "https://api.github.com/repos/remult/remult/issues{/number}",
  "pulls_url": "https://api.github.com/repos/remult/remult/pulls{/number}",
  "milestones_url": "https://api.github.com/repos/remult/remult/milestones{/number}",
  "notifications_url": "https://api.github.com/repos/remult/remult/notifications{?since,all,participating}",
  "labels_url": "https://api.github.com/repos/remult/remult/labels{/name}",
  "releases_url": "https://api.github.com/repos/remult/remult/releases{/id}",
  "deployments_url": "https://api.github.com/repos/remult/remult/deployments",
  "created_at": "2017-10-30T15:55:17Z",
  "updated_at": "2024-01-21T11:17:07Z",
  "pushed_at": "2024-01-21T13:11:31Z",
  "git_url": "git://github.com/remult/remult.git",
  "ssh_url": "git@github.com:remult/remult.git",
  "clone_url": "https://github.com/remult/remult.git",
  "svn_url": "https://github.com/remult/remult",
  "homepage": "https://remult.dev",
  "size": 32873,
  "stargazers_count": 2462,
  "watchers_count": 2462,
  "language": "TypeScript",
  "has_issues": true,
  "has_projects": true,
  "has_downloads": true,
  "has_wiki": true,
  "has_pages": false,
  "has_discussions": true,
  "forks_count": 102,
  "mirror_url": null,
  "archived": false,
  "disabled": false,
  "open_issues_count": 46,
  "license": {
    "key": "mit",
    "name": "MIT License",
    "spdx_id": "MIT",
    "url": "https://api.github.com/licenses/mit",
    "node_id": "MDc6TGljZW5zZTEz"
  },
  "allow_forking": true,
  "is_template": false,
  "web_commit_signoff_required": false,
  "topics": [
    "angular",
    "api",
    "crud",
    "express-middleware",
    "fullstack",
    "fullstack-typescript",
    "jamstack",
    "nextjs",
    "orm",
    "postgresql",
    "react",
    "rest",
    "typescript",
    "validation",
    "vue"
  ],
  "visibility": "public",
  "forks": 102,
  "open_issues": 46,
  "watchers": 2462,
  "default_branch": "master",
  "permissions": {
    "admin": false,
    "maintain": false,
    "push": false,
    "triage": false,
    "pull": false
  },
  "_index": 1218
}