{
  "id": 228791176,
  "node_id": "MDEwOlJlcG9zaXRvcnkyMjg3OTExNzY=",
  "name": "phasen",
  "full_name": "huyanxin/phasen",
  "private": false,
  "owner": {
    "login": "huyanxin",
    "id": 16916787,
    "node_id": "MDQ6VXNlcjE2OTE2Nzg3",
    "avatar_url": "https://avatars.githubusercontent.com/u/16916787?v=4",
    "gravatar_id": "",
    "url": "https://api.github.com/users/huyanxin",
    "html_url": "https://github.com/huyanxin",
    "followers_url": "https://api.github.com/users/huyanxin/followers",
    "following_url": "https://api.github.com/users/huyanxin/following{/other_user}",
    "gists_url": "https://api.github.com/users/huyanxin/gists{/gist_id}",
    "starred_url": "https://api.github.com/users/huyanxin/starred{/owner}{/repo}",
    "subscriptions_url": "https://api.github.com/users/huyanxin/subscriptions",
    "organizations_url": "https://api.github.com/users/huyanxin/orgs",
    "repos_url": "https://api.github.com/users/huyanxin/repos",
    "events_url": "https://api.github.com/users/huyanxin/events{/privacy}",
    "received_events_url": "https://api.github.com/users/huyanxin/received_events",
    "type": "User",
    "site_admin": false
  },
  "html_url": "https://github.com/huyanxin/phasen",
  "description": "A unofficial Pytorch implementation of Microsoft's PHASEN",
  "fork": false,
  "url": "https://api.github.com/repos/huyanxin/phasen",
  "forks_url": "https://api.github.com/repos/huyanxin/phasen/forks",
  "keys_url": "https://api.github.com/repos/huyanxin/phasen/keys{/key_id}",
  "collaborators_url": "https://api.github.com/repos/huyanxin/phasen/collaborators{/collaborator}",
  "teams_url": "https://api.github.com/repos/huyanxin/phasen/teams",
  "hooks_url": "https://api.github.com/repos/huyanxin/phasen/hooks",
  "issue_events_url": "https://api.github.com/repos/huyanxin/phasen/issues/events{/number}",
  "events_url": "https://api.github.com/repos/huyanxin/phasen/events",
  "assignees_url": "https://api.github.com/repos/huyanxin/phasen/assignees{/user}",
  "branches_url": "https://api.github.com/repos/huyanxin/phasen/branches{/branch}",
  "tags_url": "https://api.github.com/repos/huyanxin/phasen/tags",
  "blobs_url": "https://api.github.com/repos/huyanxin/phasen/git/blobs{/sha}",
  "git_tags_url": "https://api.github.com/repos/huyanxin/phasen/git/tags{/sha}",
  "git_refs_url": "https://api.github.com/repos/huyanxin/phasen/git/refs{/sha}",
  "trees_url": "https://api.github.com/repos/huyanxin/phasen/git/trees{/sha}",
  "statuses_url": "https://api.github.com/repos/huyanxin/phasen/statuses/{sha}",
  "languages_url": "https://api.github.com/repos/huyanxin/phasen/languages",
  "stargazers_url": "https://api.github.com/repos/huyanxin/phasen/stargazers",
  "contributors_url": "https://api.github.com/repos/huyanxin/phasen/contributors",
  "subscribers_url": "https://api.github.com/repos/huyanxin/phasen/subscribers",
  "subscription_url": "https://api.github.com/repos/huyanxin/phasen/subscription",
  "commits_url": "https://api.github.com/repos/huyanxin/phasen/commits{/sha}",
  "git_commits_url": "https://api.github.com/repos/huyanxin/phasen/git/commits{/sha}",
  "comments_url": "https://api.github.com/repos/huyanxin/phasen/comments{/number}",
  "issue_comment_url": "https://api.github.com/repos/huyanxin/phasen/issues/comments{/number}",
  "contents_url": "https://api.github.com/repos/huyanxin/phasen/contents/{+path}",
  "compare_url": "https://api.github.com/repos/huyanxin/phasen/compare/{base}...{head}",
  "merges_url": "https://api.github.com/repos/huyanxin/phasen/merges",
  "archive_url": "https://api.github.com/repos/huyanxin/phasen/{archive_format}{/ref}",
  "downloads_url": "https://api.github.com/repos/huyanxin/phasen/downloads",
  "issues_url": "https://api.github.com/repos/huyanxin/phasen/issues{/number}",
  "pulls_url": "https://api.github.com/repos/huyanxin/phasen/pulls{/number}",
  "milestones_url": "https://api.github.com/repos/huyanxin/phasen/milestones{/number}",
  "notifications_url": "https://api.github.com/repos/huyanxin/phasen/notifications{?since,all,participating}",
  "labels_url": "https://api.github.com/repos/huyanxin/phasen/labels{/name}",
  "releases_url": "https://api.github.com/repos/huyanxin/phasen/releases{/id}",
  "deployments_url": "https://api.github.com/repos/huyanxin/phasen/deployments",
  "created_at": "2019-12-18T08:15:43Z",
  "updated_at": "2024-02-13T11:57:24Z",
  "pushed_at": "2020-02-18T08:35:16Z",
  "git_url": "git://github.com/huyanxin/phasen.git",
  "ssh_url": "git@github.com:huyanxin/phasen.git",
  "clone_url": "https://github.com/huyanxin/phasen.git",
  "svn_url": "https://github.com/huyanxin/phasen",
  "homepage": null,
  "size": 2166,
  "stargazers_count": 205,
  "watchers_count": 205,
  "language": "Python",
  "has_issues": true,
  "has_projects": true,
  "has_downloads": true,
  "has_wiki": true,
  "has_pages": false,
  "has_discussions": false,
  "forks_count": 47,
  "mirror_url": null,
  "archived": false,
  "disabled": false,
  "open_issues_count": 9,
  "license": null,
  "allow_forking": true,
  "is_template": false,
  "web_commit_signoff_required": false,
  "topics": [
    "pytorch",
    "pytorch-implementation",
    "speech-enhancement"
  ],
  "visibility": "public",
  "forks": 47,
  "open_issues": 9,
  "watchers": 205,
  "default_branch": "master",
  "permissions": {
    "admin": false,
    "maintain": false,
    "push": false,
    "triage": false,
    "pull": false
  },
  "_index": 250
}