{
  "id": 42421550,
  "node_id": "MDEwOlJlcG9zaXRvcnk0MjQyMTU1MA==",
  "name": "RxMarkdown",
  "full_name": "yydcdut/RxMarkdown",
  "private": false,
  "owner": {
    "login": "yydcdut",
    "id": 7722279,
    "node_id": "MDQ6VXNlcjc3MjIyNzk=",
    "avatar_url": "https://avatars.githubusercontent.com/u/7722279?v=4",
    "gravatar_id": "",
    "url": "https://api.github.com/users/yydcdut",
    "html_url": "https://github.com/yydcdut",
    "followers_url": "https://api.github.com/users/yydcdut/followers",
    "following_url": "https://api.github.com/users/yydcdut/following{/other_user}",
    "gists_url": "https://api.github.com/users/yydcdut/gists{/gist_id}",
    "starred_url": "https://api.github.com/users/yydcdut/starred{/owner}{/repo}",
    "subscriptions_url": "https://api.github.com/users/yydcdut/subscriptions",
    "organizations_url": "https://api.github.com/users/yydcdut/orgs",
    "repos_url": "https://api.github.com/users/yydcdut/repos",
    "events_url": "https://api.github.com/users/yydcdut/events{/privacy}",
    "received_events_url": "https://api.github.com/users/yydcdut/received_events",
    "type": "User",
    "site_admin": false
  },
  "html_url": "https://github.com/yydcdut/RxMarkdown",
  "description": ":fax:Markdown for Android, supports TextView && EditText (Live Preview), supports code high light.",
  "fork": false,
  "url": "https://api.github.com/repos/yydcdut/RxMarkdown",
  "forks_url": "https://api.github.com/repos/yydcdut/RxMarkdown/forks",
  "keys_url": "https://api.github.com/repos/yydcdut/RxMarkdown/keys{/key_id}",
  "collaborators_url": "https://api.github.com/repos/yydcdut/RxMarkdown/collaborators{/collaborator}",
  "teams_url": "https://api.github.com/repos/yydcdut/RxMarkdown/teams",
  "hooks_url": "https://api.github.com/repos/yydcdut/RxMarkdown/hooks",
  "issue_events_url": "https://api.github.com/repos/yydcdut/RxMarkdown/issues/events{/number}",
  "events_url": "https://api.github.com/repos/yydcdut/RxMarkdown/events",
  "assignees_url": "https://api.github.com/repos/yydcdut/RxMarkdown/assignees{/user}",
  "branches_url": "https://api.github.com/repos/yydcdut/RxMarkdown/branches{/branch}",
  "tags_url": "https://api.github.com/repos/yydcdut/RxMarkdown/tags",
  "blobs_url": "https://api.github.com/repos/yydcdut/RxMarkdown/git/blobs{/sha}",
  "git_tags_url": "https://api.github.com/repos/yydcdut/RxMarkdown/git/tags{/sha}",
  "git_refs_url": "https://api.github.com/repos/yydcdut/RxMarkdown/git/refs{/sha}",
  "trees_url": "https://api.github.com/repos/yydcdut/RxMarkdown/git/trees{/sha}",
  "statuses_url": "https://api.github.com/repos/yydcdut/RxMarkdown/statuses/{sha}",
  "languages_url": "https://api.github.com/repos/yydcdut/RxMarkdown/languages",
  "stargazers_url": "https://api.github.com/repos/yydcdut/RxMarkdown/stargazers",
  "contributors_url": "https://api.github.com/repos/yydcdut/RxMarkdown/contributors",
  "subscribers_url": "https://api.github.com/repos/yydcdut/RxMarkdown/subscribers",
  "subscription_url": "https://api.github.com/repos/yydcdut/RxMarkdown/subscription",
  "commits_url": "https://api.github.com/repos/yydcdut/RxMarkdown/commits{/sha}",
  "git_commits_url": "https://api.github.com/repos/yydcdut/RxMarkdown/git/commits{/sha}",
  "comments_url": "https://api.github.com/repos/yydcdut/RxMarkdown/comments{/number}",
  "issue_comment_url": "https://api.github.com/repos/yydcdut/RxMarkdown/issues/comments{/number}",
  "contents_url": "https://api.github.com/repos/yydcdut/RxMarkdown/contents/{+path}",
  "compare_url": "https://api.github.com/repos/yydcdut/RxMarkdown/compare/{base}...{head}",
  "merges_url": "https://api.github.com/repos/yydcdut/RxMarkdown/merges",
  "archive_url": "https://api.github.com/repos/yydcdut/RxMarkdown/{archive_format}{/ref}",
  "downloads_url": "https://api.github.com/repos/yydcdut/RxMarkdown/downloads",
  "issues_url": "https://api.github.com/repos/yydcdut/RxMarkdown/issues{/number}",
  "pulls_url": "https://api.github.com/repos/yydcdut/RxMarkdown/pulls{/number}",
  "milestones_url": "https://api.github.com/repos/yydcdut/RxMarkdown/milestones{/number}",
  "notifications_url": "https://api.github.com/repos/yydcdut/RxMarkdown/notifications{?since,all,participating}",
  "labels_url": "https://api.github.com/repos/yydcdut/RxMarkdown/labels{/name}",
  "releases_url": "https://api.github.com/repos/yydcdut/RxMarkdown/releases{/id}",
  "deployments_url": "https://api.github.com/repos/yydcdut/RxMarkdown/deployments",
  "created_at": "2015-09-14T02:05:39Z",
  "updated_at": "2023-03-02T03:24:55Z",
  "pushed_at": "2020-07-24T07:48:41Z",
  "git_url": "git://github.com/yydcdut/RxMarkdown.git",
  "ssh_url": "git@github.com:yydcdut/RxMarkdown.git",
  "clone_url": "https://github.com/yydcdut/RxMarkdown.git",
  "svn_url": "https://github.com/yydcdut/RxMarkdown",
  "homepage": "",
  "size": 21625,
  "stargazers_count": 733,
  "watchers_count": 733,
  "language": "Java",
  "has_issues": true,
  "has_projects": true,
  "has_downloads": true,
  "has_wiki": true,
  "has_pages": false,
  "has_discussions": false,
  "forks_count": 95,
  "mirror_url": null,
  "archived": false,
  "disabled": false,
  "open_issues_count": 27,
  "license": null,
  "allow_forking": true,
  "is_template": false,
  "web_commit_signoff_required": false,
  "topics": [
    "android",
    "android-library",
    "android-textview",
    "edittext",
    "highlight",
    "markdown",
    "rxandroid",
    "rxjava",
    "spannable",
    "spannablestring",
    "spannablestringbuilder",
    "textview"
  ],
  "visibility": "public",
  "forks": 95,
  "open_issues": 27,
  "watchers": 733,
  "default_branch": "master",
  "permissions": {
    "admin": false,
    "maintain": false,
    "push": false,
    "triage": false,
    "pull": false
  },
  "_index": 1569
}