{
  "id": 199345967,
  "node_id": "MDEwOlJlcG9zaXRvcnkxOTkzNDU5Njc=",
  "name": "vue-moveable",
  "full_name": "probil/vue-moveable",
  "private": false,
  "owner": {
    "login": "probil",
    "id": 6773202,
    "node_id": "MDQ6VXNlcjY3NzMyMDI=",
    "avatar_url": "https://avatars.githubusercontent.com/u/6773202?v=4",
    "gravatar_id": "",
    "url": "https://api.github.com/users/probil",
    "html_url": "https://github.com/probil",
    "followers_url": "https://api.github.com/users/probil/followers",
    "following_url": "https://api.github.com/users/probil/following{/other_user}",
    "gists_url": "https://api.github.com/users/probil/gists{/gist_id}",
    "starred_url": "https://api.github.com/users/probil/starred{/owner}{/repo}",
    "subscriptions_url": "https://api.github.com/users/probil/subscriptions",
    "organizations_url": "https://api.github.com/users/probil/orgs",
    "repos_url": "https://api.github.com/users/probil/repos",
    "events_url": "https://api.github.com/users/probil/events{/privacy}",
    "received_events_url": "https://api.github.com/users/probil/received_events",
    "type": "User",
    "site_admin": false
  },
  "html_url": "https://github.com/probil/vue-moveable",
  "description": "↔️ ↕️ 🔄  Vue.js wrapper for Moveable",
  "fork": false,
  "url": "https://api.github.com/repos/probil/vue-moveable",
  "forks_url": "https://api.github.com/repos/probil/vue-moveable/forks",
  "keys_url": "https://api.github.com/repos/probil/vue-moveable/keys{/key_id}",
  "collaborators_url": "https://api.github.com/repos/probil/vue-moveable/collaborators{/collaborator}",
  "teams_url": "https://api.github.com/repos/probil/vue-moveable/teams",
  "hooks_url": "https://api.github.com/repos/probil/vue-moveable/hooks",
  "issue_events_url": "https://api.github.com/repos/probil/vue-moveable/issues/events{/number}",
  "events_url": "https://api.github.com/repos/probil/vue-moveable/events",
  "assignees_url": "https://api.github.com/repos/probil/vue-moveable/assignees{/user}",
  "branches_url": "https://api.github.com/repos/probil/vue-moveable/branches{/branch}",
  "tags_url": "https://api.github.com/repos/probil/vue-moveable/tags",
  "blobs_url": "https://api.github.com/repos/probil/vue-moveable/git/blobs{/sha}",
  "git_tags_url": "https://api.github.com/repos/probil/vue-moveable/git/tags{/sha}",
  "git_refs_url": "https://api.github.com/repos/probil/vue-moveable/git/refs{/sha}",
  "trees_url": "https://api.github.com/repos/probil/vue-moveable/git/trees{/sha}",
  "statuses_url": "https://api.github.com/repos/probil/vue-moveable/statuses/{sha}",
  "languages_url": "https://api.github.com/repos/probil/vue-moveable/languages",
  "stargazers_url": "https://api.github.com/repos/probil/vue-moveable/stargazers",
  "contributors_url": "https://api.github.com/repos/probil/vue-moveable/contributors",
  "subscribers_url": "https://api.github.com/repos/probil/vue-moveable/subscribers",
  "subscription_url": "https://api.github.com/repos/probil/vue-moveable/subscription",
  "commits_url": "https://api.github.com/repos/probil/vue-moveable/commits{/sha}",
  "git_commits_url": "https://api.github.com/repos/probil/vue-moveable/git/commits{/sha}",
  "comments_url": "https://api.github.com/repos/probil/vue-moveable/comments{/number}",
  "issue_comment_url": "https://api.github.com/repos/probil/vue-moveable/issues/comments{/number}",
  "contents_url": "https://api.github.com/repos/probil/vue-moveable/contents/{+path}",
  "compare_url": "https://api.github.com/repos/probil/vue-moveable/compare/{base}...{head}",
  "merges_url": "https://api.github.com/repos/probil/vue-moveable/merges",
  "archive_url": "https://api.github.com/repos/probil/vue-moveable/{archive_format}{/ref}",
  "downloads_url": "https://api.github.com/repos/probil/vue-moveable/downloads",
  "issues_url": "https://api.github.com/repos/probil/vue-moveable/issues{/number}",
  "pulls_url": "https://api.github.com/repos/probil/vue-moveable/pulls{/number}",
  "milestones_url": "https://api.github.com/repos/probil/vue-moveable/milestones{/number}",
  "notifications_url": "https://api.github.com/repos/probil/vue-moveable/notifications{?since,all,participating}",
  "labels_url": "https://api.github.com/repos/probil/vue-moveable/labels{/name}",
  "releases_url": "https://api.github.com/repos/probil/vue-moveable/releases{/id}",
  "deployments_url": "https://api.github.com/repos/probil/vue-moveable/deployments",
  "created_at": "2019-07-28T23:08:10Z",
  "updated_at": "2022-11-24T17:08:30Z",
  "pushed_at": "2021-11-09T12:52:30Z",
  "git_url": "git://github.com/probil/vue-moveable.git",
  "ssh_url": "git@github.com:probil/vue-moveable.git",
  "clone_url": "https://github.com/probil/vue-moveable.git",
  "svn_url": "https://github.com/probil/vue-moveable",
  "homepage": "https://vue-moveable.netlify.com/",
  "size": 5562,
  "stargazers_count": 956,
  "watchers_count": 956,
  "language": "Vue",
  "has_issues": true,
  "has_projects": true,
  "has_downloads": true,
  "has_wiki": false,
  "has_pages": false,
  "has_discussions": false,
  "forks_count": 67,
  "mirror_url": null,
  "archived": true,
  "disabled": false,
  "open_issues_count": 46,
  "license": {
    "key": "mit",
    "name": "MIT License",
    "spdx_id": "MIT",
    "url": "https://api.github.com/licenses/mit",
    "node_id": "MDc6TGljZW5zZTEz"
  },
  "allow_forking": true,
  "is_template": false,
  "web_commit_signoff_required": false,
  "topics": [
    "draggable",
    "moveable",
    "resizable",
    "rotatable",
    "scalable",
    "vue",
    "vue-moveable",
    "warpable"
  ],
  "visibility": "public",
  "forks": 67,
  "open_issues": 46,
  "watchers": 956,
  "default_branch": "master",
  "permissions": {
    "admin": false,
    "maintain": false,
    "push": false,
    "triage": false,
    "pull": false
  },
  "_index": 1370
}