{
  "id": 464827989,
  "node_id": "R_kgDOG7S2VQ",
  "name": "jsonhero-web",
  "full_name": "apihero-run/jsonhero-web",
  "private": false,
  "owner": {
    "login": "apihero-run",
    "id": 95297378,
    "node_id": "O_kgDOBa4fYg",
    "avatar_url": "https://avatars.githubusercontent.com/u/95297378?v=4",
    "gravatar_id": "",
    "url": "https://api.github.com/users/apihero-run",
    "html_url": "https://github.com/apihero-run",
    "followers_url": "https://api.github.com/users/apihero-run/followers",
    "following_url": "https://api.github.com/users/apihero-run/following{/other_user}",
    "gists_url": "https://api.github.com/users/apihero-run/gists{/gist_id}",
    "starred_url": "https://api.github.com/users/apihero-run/starred{/owner}{/repo}",
    "subscriptions_url": "https://api.github.com/users/apihero-run/subscriptions",
    "organizations_url": "https://api.github.com/users/apihero-run/orgs",
    "repos_url": "https://api.github.com/users/apihero-run/repos",
    "events_url": "https://api.github.com/users/apihero-run/events{/privacy}",
    "received_events_url": "https://api.github.com/users/apihero-run/received_events",
    "type": "Organization",
    "site_admin": false
  },
  "html_url": "https://github.com/apihero-run/jsonhero-web",
  "description": "JSON Hero is an open-source, beautiful JSON explorer for the web that lets you browse, search and navigate your JSON files at speed. 🚀",
  "fork": false,
  "url": "https://api.github.com/repos/apihero-run/jsonhero-web",
  "forks_url": "https://api.github.com/repos/apihero-run/jsonhero-web/forks",
  "keys_url": "https://api.github.com/repos/apihero-run/jsonhero-web/keys{/key_id}",
  "collaborators_url": "https://api.github.com/repos/apihero-run/jsonhero-web/collaborators{/collaborator}",
  "teams_url": "https://api.github.com/repos/apihero-run/jsonhero-web/teams",
  "hooks_url": "https://api.github.com/repos/apihero-run/jsonhero-web/hooks",
  "issue_events_url": "https://api.github.com/repos/apihero-run/jsonhero-web/issues/events{/number}",
  "events_url": "https://api.github.com/repos/apihero-run/jsonhero-web/events",
  "assignees_url": "https://api.github.com/repos/apihero-run/jsonhero-web/assignees{/user}",
  "branches_url": "https://api.github.com/repos/apihero-run/jsonhero-web/branches{/branch}",
  "tags_url": "https://api.github.com/repos/apihero-run/jsonhero-web/tags",
  "blobs_url": "https://api.github.com/repos/apihero-run/jsonhero-web/git/blobs{/sha}",
  "git_tags_url": "https://api.github.com/repos/apihero-run/jsonhero-web/git/tags{/sha}",
  "git_refs_url": "https://api.github.com/repos/apihero-run/jsonhero-web/git/refs{/sha}",
  "trees_url": "https://api.github.com/repos/apihero-run/jsonhero-web/git/trees{/sha}",
  "statuses_url": "https://api.github.com/repos/apihero-run/jsonhero-web/statuses/{sha}",
  "languages_url": "https://api.github.com/repos/apihero-run/jsonhero-web/languages",
  "stargazers_url": "https://api.github.com/repos/apihero-run/jsonhero-web/stargazers",
  "contributors_url": "https://api.github.com/repos/apihero-run/jsonhero-web/contributors",
  "subscribers_url": "https://api.github.com/repos/apihero-run/jsonhero-web/subscribers",
  "subscription_url": "https://api.github.com/repos/apihero-run/jsonhero-web/subscription",
  "commits_url": "https://api.github.com/repos/apihero-run/jsonhero-web/commits{/sha}",
  "git_commits_url": "https://api.github.com/repos/apihero-run/jsonhero-web/git/commits{/sha}",
  "comments_url": "https://api.github.com/repos/apihero-run/jsonhero-web/comments{/number}",
  "issue_comment_url": "https://api.github.com/repos/apihero-run/jsonhero-web/issues/comments{/number}",
  "contents_url": "https://api.github.com/repos/apihero-run/jsonhero-web/contents/{+path}",
  "compare_url": "https://api.github.com/repos/apihero-run/jsonhero-web/compare/{base}...{head}",
  "merges_url": "https://api.github.com/repos/apihero-run/jsonhero-web/merges",
  "archive_url": "https://api.github.com/repos/apihero-run/jsonhero-web/{archive_format}{/ref}",
  "downloads_url": "https://api.github.com/repos/apihero-run/jsonhero-web/downloads",
  "issues_url": "https://api.github.com/repos/apihero-run/jsonhero-web/issues{/number}",
  "pulls_url": "https://api.github.com/repos/apihero-run/jsonhero-web/pulls{/number}",
  "milestones_url": "https://api.github.com/repos/apihero-run/jsonhero-web/milestones{/number}",
  "notifications_url": "https://api.github.com/repos/apihero-run/jsonhero-web/notifications{?since,all,participating}",
  "labels_url": "https://api.github.com/repos/apihero-run/jsonhero-web/labels{/name}",
  "releases_url": "https://api.github.com/repos/apihero-run/jsonhero-web/releases{/id}",
  "deployments_url": "https://api.github.com/repos/apihero-run/jsonhero-web/deployments",
  "created_at": "2022-03-01T09:33:29Z",
  "updated_at": "2022-12-10T23:58:58Z",
  "pushed_at": "2022-12-07T12:18:00Z",
  "git_url": "git://github.com/apihero-run/jsonhero-web.git",
  "ssh_url": "git@github.com:apihero-run/jsonhero-web.git",
  "clone_url": "https://github.com/apihero-run/jsonhero-web.git",
  "svn_url": "https://github.com/apihero-run/jsonhero-web",
  "homepage": "https://jsonhero.io",
  "size": 58357,
  "stargazers_count": 7058,
  "watchers_count": 7058,
  "language": "TypeScript",
  "has_issues": true,
  "has_projects": true,
  "has_downloads": true,
  "has_wiki": true,
  "has_pages": false,
  "has_discussions": true,
  "forks_count": 297,
  "mirror_url": null,
  "archived": false,
  "disabled": false,
  "open_issues_count": 51,
  "license": {
    "key": "apache-2.0",
    "name": "Apache License 2.0",
    "spdx_id": "Apache-2.0",
    "url": "https://api.github.com/licenses/apache-2.0",
    "node_id": "MDc6TGljZW5zZTI="
  },
  "allow_forking": true,
  "is_template": false,
  "web_commit_signoff_required": false,
  "topics": [
    "developer-tools",
    "devtools",
    "hacktoberfest",
    "json",
    "json-viewer",
    "react",
    "tools",
    "typescript",
    "viewer"
  ],
  "visibility": "public",
  "forks": 297,
  "open_issues": 51,
  "watchers": 7058,
  "default_branch": "main",
  "permissions": {
    "admin": false,
    "maintain": false,
    "push": false,
    "triage": false,
    "pull": false
  },
  "_index": 377
}