{
  "id": 44336879,
  "node_id": "MDEwOlJlcG9zaXRvcnk0NDMzNjg3OQ==",
  "name": "ReLinker",
  "full_name": "KeepSafe/ReLinker",
  "private": false,
  "owner": {
    "login": "KeepSafe",
    "id": 1377248,
    "node_id": "MDEyOk9yZ2FuaXphdGlvbjEzNzcyNDg=",
    "avatar_url": "https://avatars.githubusercontent.com/u/1377248?v=4",
    "gravatar_id": "",
    "url": "https://api.github.com/users/KeepSafe",
    "html_url": "https://github.com/KeepSafe",
    "followers_url": "https://api.github.com/users/KeepSafe/followers",
    "following_url": "https://api.github.com/users/KeepSafe/following{/other_user}",
    "gists_url": "https://api.github.com/users/KeepSafe/gists{/gist_id}",
    "starred_url": "https://api.github.com/users/KeepSafe/starred{/owner}{/repo}",
    "subscriptions_url": "https://api.github.com/users/KeepSafe/subscriptions",
    "organizations_url": "https://api.github.com/users/KeepSafe/orgs",
    "repos_url": "https://api.github.com/users/KeepSafe/repos",
    "events_url": "https://api.github.com/users/KeepSafe/events{/privacy}",
    "received_events_url": "https://api.github.com/users/KeepSafe/received_events",
    "type": "Organization",
    "site_admin": false
  },
  "html_url": "https://github.com/KeepSafe/ReLinker",
  "description": "A robust native library loader for Android.",
  "fork": false,
  "url": "https://api.github.com/repos/KeepSafe/ReLinker",
  "forks_url": "https://api.github.com/repos/KeepSafe/ReLinker/forks",
  "keys_url": "https://api.github.com/repos/KeepSafe/ReLinker/keys{/key_id}",
  "collaborators_url": "https://api.github.com/repos/KeepSafe/ReLinker/collaborators{/collaborator}",
  "teams_url": "https://api.github.com/repos/KeepSafe/ReLinker/teams",
  "hooks_url": "https://api.github.com/repos/KeepSafe/ReLinker/hooks",
  "issue_events_url": "https://api.github.com/repos/KeepSafe/ReLinker/issues/events{/number}",
  "events_url": "https://api.github.com/repos/KeepSafe/ReLinker/events",
  "assignees_url": "https://api.github.com/repos/KeepSafe/ReLinker/assignees{/user}",
  "branches_url": "https://api.github.com/repos/KeepSafe/ReLinker/branches{/branch}",
  "tags_url": "https://api.github.com/repos/KeepSafe/ReLinker/tags",
  "blobs_url": "https://api.github.com/repos/KeepSafe/ReLinker/git/blobs{/sha}",
  "git_tags_url": "https://api.github.com/repos/KeepSafe/ReLinker/git/tags{/sha}",
  "git_refs_url": "https://api.github.com/repos/KeepSafe/ReLinker/git/refs{/sha}",
  "trees_url": "https://api.github.com/repos/KeepSafe/ReLinker/git/trees{/sha}",
  "statuses_url": "https://api.github.com/repos/KeepSafe/ReLinker/statuses/{sha}",
  "languages_url": "https://api.github.com/repos/KeepSafe/ReLinker/languages",
  "stargazers_url": "https://api.github.com/repos/KeepSafe/ReLinker/stargazers",
  "contributors_url": "https://api.github.com/repos/KeepSafe/ReLinker/contributors",
  "subscribers_url": "https://api.github.com/repos/KeepSafe/ReLinker/subscribers",
  "subscription_url": "https://api.github.com/repos/KeepSafe/ReLinker/subscription",
  "commits_url": "https://api.github.com/repos/KeepSafe/ReLinker/commits{/sha}",
  "git_commits_url": "https://api.github.com/repos/KeepSafe/ReLinker/git/commits{/sha}",
  "comments_url": "https://api.github.com/repos/KeepSafe/ReLinker/comments{/number}",
  "issue_comment_url": "https://api.github.com/repos/KeepSafe/ReLinker/issues/comments{/number}",
  "contents_url": "https://api.github.com/repos/KeepSafe/ReLinker/contents/{+path}",
  "compare_url": "https://api.github.com/repos/KeepSafe/ReLinker/compare/{base}...{head}",
  "merges_url": "https://api.github.com/repos/KeepSafe/ReLinker/merges",
  "archive_url": "https://api.github.com/repos/KeepSafe/ReLinker/{archive_format}{/ref}",
  "downloads_url": "https://api.github.com/repos/KeepSafe/ReLinker/downloads",
  "issues_url": "https://api.github.com/repos/KeepSafe/ReLinker/issues{/number}",
  "pulls_url": "https://api.github.com/repos/KeepSafe/ReLinker/pulls{/number}",
  "milestones_url": "https://api.github.com/repos/KeepSafe/ReLinker/milestones{/number}",
  "notifications_url": "https://api.github.com/repos/KeepSafe/ReLinker/notifications{?since,all,participating}",
  "labels_url": "https://api.github.com/repos/KeepSafe/ReLinker/labels{/name}",
  "releases_url": "https://api.github.com/repos/KeepSafe/ReLinker/releases{/id}",
  "deployments_url": "https://api.github.com/repos/KeepSafe/ReLinker/deployments",
  "created_at": "2015-10-15T18:23:00Z",
  "updated_at": "2023-09-02T08:12:18Z",
  "pushed_at": "2022-10-26T10:31:55Z",
  "git_url": "git://github.com/KeepSafe/ReLinker.git",
  "ssh_url": "git@github.com:KeepSafe/ReLinker.git",
  "clone_url": "https://github.com/KeepSafe/ReLinker.git",
  "svn_url": "https://github.com/KeepSafe/ReLinker",
  "homepage": "",
  "size": 335,
  "stargazers_count": 3037,
  "watchers_count": 3037,
  "language": "Java",
  "has_issues": true,
  "has_projects": false,
  "has_downloads": true,
  "has_wiki": true,
  "has_pages": false,
  "has_discussions": false,
  "forks_count": 363,
  "mirror_url": null,
  "archived": false,
  "disabled": false,
  "open_issues_count": 22,
  "license": {
    "key": "apache-2.0",
    "name": "Apache License 2.0",
    "spdx_id": "Apache-2.0",
    "url": "https://api.github.com/licenses/apache-2.0",
    "node_id": "MDc6TGljZW5zZTI="
  },
  "allow_forking": true,
  "is_template": false,
  "web_commit_signoff_required": false,
  "topics": [
    "android",
    "android-ndk",
    "jni",
    "native-libraries",
    "ndk"
  ],
  "visibility": "public",
  "forks": 363,
  "open_issues": 22,
  "watchers": 3037,
  "default_branch": "master",
  "permissions": {
    "admin": false,
    "maintain": false,
    "push": false,
    "triage": false,
    "pull": false
  },
  "_index": 2027
}